dsawl
