Metadata-Version: 1.2
Name: dsawl
Version: 0.1.1
Summary: A set of tools for machine learning
Home-page: https://github.com/Nikolay-Lysenko/dsawl
Author: Nikolay Lysenko
Author-email: nikolay.lysenko.1992@gmail.com
License: MIT
Keywords: active_learning categorical_features feature_engineering
Platform: UNKNOWN
Requires-Python: >=3.5
